MANIFEST.in
README.md
setup.py
django_parsesync.egg-info/PKG-INFO
django_parsesync.egg-info/SOURCES.txt
django_parsesync.egg-info/dependency_links.txt
django_parsesync.egg-info/not-zip-safe
django_parsesync.egg-info/pbr.json
django_parsesync.egg-info/requires.txt
django_parsesync.egg-info/top_level.txt
parsesync/__init__.py
parsesync/admin.py
parsesync/client.py
parsesync/config.py
parsesync/models.py
parsesync/tests.py
parsesync/management/__init__.py
parsesync/management/commands/__init__.py
parsesync/management/commands/parsetodjango.py